mocaplib/__init__.py
mocaplib/btkapp.py
mocaplib/gapfill.py
mocaplib-0.0.8.dist-info/LICENSE
mocaplib-0.0.8.dist-info/METADATA
mocaplib-0.0.8.dist-info/WHEEL
mocaplib-0.0.8.dist-info/top_level.txt
mocaplib-0.0.8.dist-info/RECORD
