Metadata-Version: 2.1
Name: mocaplib
Version: 0.0.8
Summary: Library for Motion Capture data processing and analysis
Home-page: https://github.com/mkjung99/mocaplib
Author: Moon Ki Jung
Author-email: m.k.jung@outlook.com
License: UNKNOWN
Platform: UNKNOWN
Classifier: Programming Language :: Python :: 3
Classifier: License :: OSI Approved :: MIT License
Classifier: Operating System :: OS Independent
Requires-Python: >=3.7
